pressenter2exit/__init__.py
pressenter2exit/__version__.py
pressenter2exit/pressenter2exit.py
pressenter2exit/pressenter2exitgui.py
pressenter2exit/py.typed
pressenter2exit-0.3.1.dist-info/LICENSE
pressenter2exit-0.3.1.dist-info/LICENSE.txt
pressenter2exit-0.3.1.dist-info/METADATA
pressenter2exit-0.3.1.dist-info/WHEEL
pressenter2exit-0.3.1.dist-info/top_level.txt
pressenter2exit-0.3.1.dist-info/RECORD
