Metadata-Version: 2.1
Name: pressenter2exit
Version: 0.3.1
Summary: Facilitates exit of a Python CLI or GUI program in a controlled way
Home-page: https://github.com/jamesabel/pressenter2exit
Download-URL: https://github.com/jamesabel/pressenter2exit/archive/master.zip
Author: James Abel
Author-email: j@abel.co
License: MIT License
Keywords: cli,gui,exit,control
License-File: LICENSE
License-File: LICENSE.txt
